augmentix/__init__.py
augmentix/augmentor.py
augmentix/main.py
augmentix/process_augmentor.py
augmentix/utils.py
augmentiX-0.0.10.dist-info/LICENSE
augmentiX-0.0.10.dist-info/METADATA
augmentiX-0.0.10.dist-info/WHEEL
augmentiX-0.0.10.dist-info/entry_points.txt
augmentiX-0.0.10.dist-info/top_level.txt
augmentiX-0.0.10.dist-info/RECORD
