Metadata-Version: 2.1
Name: augmentiX
Version: 0.0.10
Summary: AugmentiX is a image augmentation library for populating YOLO datasets
Home-page: https://github.com/suryan-s/AugmentiX
Author: s-suryan
Author-email: suryannasa@gmail.com
License: MIT
Classifier: Programming Language :: Python :: 3
Classifier: License :: OSI Approved :: MIT License
Classifier: Topic :: Software Development :: Libraries
Classifier: Operating System :: OS Independent
Requires-Python: >=3.10
License-File: LICENSE
Requires-Dist: opencv-python
Requires-Dist: setuptools
Requires-Dist: tqdm
Requires-Dist: scikit-learn
Requires-Dist: numpy
Requires-Dist: pybboxes
Requires-Dist: eel
